imio.smartweb.common-1.2.43-py3.12-nspkg.pth
imio/smartweb/common/__init__.py
imio/smartweb/common/adapters.py
imio/smartweb/common/adapters.zcml
imio/smartweb/common/caching.py
imio/smartweb/common/caching_overrides.zcml
imio/smartweb/common/config.py
imio/smartweb/common/configure.zcml
imio/smartweb/common/contact_utils.py
imio/smartweb/common/indexers.py
imio/smartweb/common/indexers.zcml
imio/smartweb/common/interfaces.py
imio/smartweb/common/permissions.zcml
imio/smartweb/common/privacy.py
imio/smartweb/common/privacy.zcml
imio/smartweb/common/profiles.zcml
imio/smartweb/common/setuphandlers.py
imio/smartweb/common/subscribers.py
imio/smartweb/common/subscribers.zcml
imio/smartweb/common/testing.py
imio/smartweb/common/testing.zcml
imio/smartweb/common/utility_overrides.zcml
imio/smartweb/common/utils.py
imio/smartweb/common/vocabularies.py
imio/smartweb/common/vocabularies.zcml
imio/smartweb/common/widgets.zcml
imio/smartweb/common/behaviors/__init__.py
imio/smartweb/common/behaviors/configure.zcml
imio/smartweb/common/behaviors/iam.py
imio/smartweb/common/behaviors/topics.py
imio/smartweb/common/browser/__init__.py
imio/smartweb/common/browser/collective_taxonomy_controlpanel.py
imio/smartweb/common/browser/configure.zcml
imio/smartweb/common/browser/cropping.py
imio/smartweb/common/browser/description.pt
imio/smartweb/common/browser/description.py
imio/smartweb/common/browser/edit_taxonomy_data.pt
imio/smartweb/common/browser/forms.py
imio/smartweb/common/browser/scaling.py
imio/smartweb/common/browser/vocabulary.py
imio/smartweb/common/browser/overrides/plone.app.z3cform.templates.widget.pt
imio/smartweb/common/browser/privacy/__init__.py
imio/smartweb/common/browser/privacy/configure.zcml
imio/smartweb/common/browser/privacy/form.py
imio/smartweb/common/browser/privacy/utils.py
imio/smartweb/common/browser/privacy/views.py
imio/smartweb/common/browser/static/Makefile
imio/smartweb/common/browser/static/package.json
imio_smartweb_common-1.2.43.dist-info/licenses/LICENSE.GPL
imio_smartweb_common-1.2.43.dist-info/licenses/LICENSE.rst
imio_smartweb_common-1.2.43.dist-info/METADATA
imio_smartweb_common-1.2.43.dist-info/WHEEL
imio_smartweb_common-1.2.43.dist-info/namespace_packages.txt
imio_smartweb_common-1.2.43.dist-info/top_level.txt
imio_smartweb_common-1.2.43.dist-info/RECORD
