Metadata-Version: 2.4
Name: imio.smartweb.common
Version: 1.2.43
Summary: Common utilities, vocabularies, taxonomies for imio.smartweb & co products
Home-page: https://github.com/imio/imio.smartweb.common
Author: iMio
Author-email: christophe.boulanger@imio.be
License: GPL version 2
Project-URL: PyPI, https://pypi.python.org/pypi/imio.smartweb.common
Project-URL: Source, https://github.com/imio/imio.smartweb.common
Project-URL: Tracker, https://github.com/imio/imio.smartweb.common/issues
Keywords: Python Plone CMS
Classifier: Development Status :: 5 - Production/Stable
Classifier: Environment :: Web Environment
Classifier: Framework :: Plone
Classifier: Framework :: Plone :: Addon
Classifier: Framework :: Plone :: 6.0
Classifier: Framework :: Plone :: 6.1
Classifier: Programming Language :: Python
Classifier: Programming Language :: Python :: 3
Classifier: Programming Language :: Python :: 3.10
Classifier: Programming Language :: Python :: 3.11
Classifier: Programming Language :: Python :: 3.12
Classifier: Programming Language :: Python :: 3.13
Classifier: Operating System :: OS Independent
Classifier: License :: OSI Approved :: GNU General Public License v2 (GPLv2)
Requires-Python: >=3.10
License-File: LICENSE.GPL
License-File: LICENSE.rst
Requires-Dist: setuptools
Requires-Dist: z3c.jbot
Requires-Dist: z3c.unconfigure
Requires-Dist: beautifulsoup4
Requires-Dist: geopy
Requires-Dist: Products.GenericSetup>=1.8.2
Requires-Dist: plone.api>=1.8.4
Requires-Dist: plone.restapi
Requires-Dist: plone.app.dexterity
Requires-Dist: plone.app.imagecropping
Requires-Dist: plone.app.lockingbehavior
Requires-Dist: plone.formwidget.geolocation
Requires-Dist: plone.schema
Requires-Dist: eea.facetednavigation
Requires-Dist: imio.gdpr
Requires-Dist: collective.privacy
Requires-Dist: collective.taxonomy
Requires-Dist: iaweb.privacy
Requires-Dist: imio.smartweb.locales
Requires-Dist: more-itertools
Provides-Extra: test
Requires-Dist: plone.app.testing; extra == "test"
Requires-Dist: plone.testing>=5.0.0; extra == "test"
Requires-Dist: plone.app.robotframework[debug]; extra == "test"
Requires-Dist: plone.restapi[test]; extra == "test"
Requires-Dist: freezegun; extra == "test"
Requires-Dist: mock; extra == "test"
Dynamic: author
Dynamic: author-email
Dynamic: classifier
Dynamic: description
Dynamic: home-page
Dynamic: keywords
Dynamic: license
Dynamic: license-file
Dynamic: project-url
Dynamic: provides-extra
Dynamic: requires-dist
Dynamic: requires-python
Dynamic: summary
